pyAutoRef/__init__.py
pyAutoRef/autoref.py
pyAutoRef/model.onnx
pyAutoRef/normalization.py
pyAutoRef/object_detection.py
pyAutoRef/post_processing.py
pyAutoRef/pre_processing.py
pyAutoRef/utils.py
pyAutoRef-2.2.1.dist-info/LICENSE
pyAutoRef-2.2.1.dist-info/METADATA
pyAutoRef-2.2.1.dist-info/WHEEL
pyAutoRef-2.2.1.dist-info/top_level.txt
pyAutoRef-2.2.1.dist-info/RECORD
