Metadata-Version: 2.1
Name: pyAutoRef
Version: 2.2.1
Summary: Python pakage to perfom AutoRef (prostate T2w MRI dual reference tissue [fat and muscle] normalization).
Home-page: https://github.com/MohammedSunoqrot/pyAutoRef
Author: Mohammed R. S. Sunoqrot
Author-email: mohammed.sunoqrot@ntnu.no
Project-URL: Bug Tracker, https://github.com/MohammedSunoqrot/pyAutoRef/issues
Classifier: Programming Language :: Python :: 3
Classifier: Programming Language :: Python :: 3.8
Classifier: Programming Language :: Python :: 3.9
Classifier: Programming Language :: Python :: 3.10
Classifier: License :: OSI Approved :: MIT License
Classifier: Operating System :: OS Independent
Requires-Python: >=3.8
License-File: LICENSE
Requires-Dist: numpy
Requires-Dist: SimpleITK
Requires-Dist: Pillow
Requires-Dist: pydicom
Requires-Dist: scikit-image
Requires-Dist: onnxruntime
Requires-Dist: matplotlib>=3.0.0
